raydium/__init__.py
raydium/config.py
raydium/constants.py
raydium/example_buy.py
raydium/example_sell.py
raydium/layouts.py
raydium/raydium.py
raydium/utils.py
raydiumsdk-0.3.0.dist-info/LICENSE
raydiumsdk-0.3.0.dist-info/METADATA
raydiumsdk-0.3.0.dist-info/WHEEL
raydiumsdk-0.3.0.dist-info/top_level.txt
raydiumsdk-0.3.0.dist-info/RECORD
