Metadata-Version: 2.1
Name: raydiumsdk
Version: 0.3.0
Summary: Solana Python API
Author: Huang
License: MIT
Classifier: License :: OSI Approved :: MIT License
Classifier: Programming Language :: Python
Classifier: Programming Language :: Python :: 3
Classifier: Environment :: Console
Classifier: Operating System :: OS Independent
Classifier: Topic :: Terminals
Classifier: Topic :: Text Processing
Classifier: Topic :: Utilities
License-File: LICENSE
Requires-Dist: solana
Requires-Dist: solders
